[
       {
              "name": "Immolation support",
              "isActive": "yes",
              "regex": "^fire$",
              "script": "",
              "isFolder": "no"
       },
       {
              "name": "Limb support",
              "isActive": "yes",
              "regex": "^limbs$",
              "script": "",
              "isFolder": "no"
       },
       {
              "name": "Aff support",
              "isActive": "yes",
              "regex": "^gaff$",
              "script": "",
              "isFolder": "no"
       }
]